meta_agent/__about__.py
meta_agent/__init__.py
meta_agent/api.py
meta_agent/bundle.py
meta_agent/bundle_generator.py
meta_agent/bundle_validator.py
meta_agent/dependency_manager.py
meta_agent/embedding_benchmark.py
meta_agent/embedding_models.py
meta_agent/embedding_search.py
meta_agent/git_utils.py
meta_agent/orchestrator.py
meta_agent/planning_engine.py
meta_agent/policy.py
meta_agent/registry.py
meta_agent/research_manager.py
meta_agent/search_docs.py
meta_agent/state_manager.py
meta_agent/sub_agent_manager.py
meta_agent/telemetry.py
meta_agent/telemetry_db.py
meta_agent/template_creator.py
meta_agent/template_docs_generator.py
meta_agent/template_engine.py
meta_agent/template_governance.py
meta_agent/template_index.py
meta_agent/template_mixer.py
meta_agent/template_registry.py
meta_agent/template_schema.py
meta_agent/template_search.py
meta_agent/template_sharing.py
meta_agent/template_validator.py
meta_agent/tool_designer.py
meta_agent/validation.py
meta_agent/agents/__init__.py
meta_agent/agents/guardrail_designer_agent.py
meta_agent/agents/tool_designer_agent.py
meta_agent/cli/.gitkeep
meta_agent/cli/__init__.py
meta_agent/cli/embedding_benchmark.py
meta_agent/cli/main.py
meta_agent/data/golden_spec_fuzz_set.yaml
meta_agent/evaluation/__init__.py
meta_agent/evaluation/execution.py
meta_agent/evaluation/harness.py
meta_agent/evaluation/reporting.py
meta_agent/evaluation/result_collection.py
meta_agent/generated_tools/__init__.py
meta_agent/generated_tools/registry.json
meta_agent/generators/__init__.py
meta_agent/generators/code_validator.py
meta_agent/generators/context_builder.py
meta_agent/generators/fallback_manager.py
meta_agent/generators/guardrail_generator.py
meta_agent/generators/implementation_injector.py
meta_agent/generators/llm_code_generator.py
meta_agent/generators/prompt_builder.py
meta_agent/generators/prompt_templates.py
meta_agent/generators/regex_patterns.py
meta_agent/generators/test_generator.py
meta_agent_cli-1.0.1.dist-info/METADATA
meta_agent_cli-1.0.1.dist-info/WHEEL
meta_agent_cli-1.0.1.dist-info/entry_points.txt
meta_agent_cli-1.0.1.dist-info/licenses/LICENSE
meta_agent_cli-1.0.1.dist-info/RECORD
