Metadata-Version: 2.4
Name: meta-agent-cli
Version: 1.0.1
Summary: Generate fully-functional AI agents from natural language specifications
Project-URL: Homepage, https://github.com/DannyMac180/meta-agent
Project-URL: Documentation, https://meta-agent.readthedocs.io/
Project-URL: Repository, https://github.com/DannyMac180/meta-agent.git
Project-URL: Issues, https://github.com/DannyMac180/meta-agent/issues
Project-URL: Changelog, https://github.com/DannyMac180/meta-agent/blob/main/CHANGELOG.md
Author-email: Danny Mac <danny@dannymac.io>
Maintainer-email: Danny Mac <danny@dannymac.io>
License: MIT License
License-File: LICENSE
Keywords: agents,ai,automation,cli,llm,openai
Classifier: Development Status :: 4 - Beta
Classifier: Environment :: Console
Classifier: Intended Audience :: Developers
Classifier: License :: OSI Approved :: MIT License
Classifier: Operating System :: OS Independent
Classifier: Programming Language :: Python :: 3
Classifier: Programming Language :: Python :: 3.11
Classifier: Programming Language :: Python :: 3.12
Classifier: Programming Language :: Python :: 3.13
Classifier: Topic :: Scientific/Engineering :: Artificial Intelligence
Classifier: Topic :: Software Development :: Code Generators
Requires-Python: >=3.11
Requires-Dist: aiohttp~=3.12
Requires-Dist: backoff<3,>=2.2
Requires-Dist: click<9,>=8.2
Requires-Dist: docker<8,>=7
Requires-Dist: jinja2<4,>=3
Requires-Dist: numpy<3,>=2
Requires-Dist: openai<2,>=1.80.0
Requires-Dist: pydantic<3,>=2.7
Requires-Dist: python-dotenv<2,>=1
Requires-Dist: pyyaml<7,>=6
Provides-Extra: test
Requires-Dist: pyright>=1.1.300; extra == 'test'
Requires-Dist: pytest-asyncio~=0.23; extra == 'test'
Requires-Dist: pytest-cov~=5.0; extra == 'test'
Requires-Dist: pytest-mock~=3.12; extra == 'test'
Requires-Dist: pytest~=8.2; extra == 'test'
